{
  "version": "v18-20260612075459",
  "latestChanges": [
    {
      "text": "직원별 현황 이미지 칸 겹침/날짜 잘림 수정",
      "roles": [
        "점장",
        "검수자",
        "관리자"
      ]
    },
    {
      "text": "직원별 현황 이미지에서 운영매장 인원만 표시",
      "roles": [
        "점장",
        "검수자",
        "관리자"
      ]
    },
    {
      "text": "배정불가/비운영 매장 항목 이미지 복사 대상 제외",
      "roles": [
        "점장",
        "검수자",
        "관리자"
      ]
    },
    {
      "text": "임시 배정 팝업 필터/버튼 수평 정렬 재수정",
      "roles": [
        "점장",
        "관리자"
      ]
    }
  ]
}